{
 "nodes":[{"name":"Adygei","size":12.2493436864878,"group":"All"}, {"name":"Balochi","size":11.8662993495436,"group":"All"}, {"name":"BantuKenya","size":10.0367877660009,"group":"All"}, {"name":"BantuSouthAfrica","size":12.8365086163604,"group":"All"}, {"name":"Basque","size":9.52825597347407,"group":"All"}, {"name":"Bedouin","size":9.45880455319475,"group":"All"}, {"name":"BiakaPygmy","size":11.1667042903625,"group":"All"}, {"name":"Burusho","size":8.85686831240139,"group":"All"}, {"name":"Cambodian","size":8.14363566874323,"group":"All"}, {"name":"Colombian","size":7.42660414615234,"group":"All"}, {"name":"Daur","size":8.72618219429418,"group":"All"}, {"name":"Druze","size":9.20251774394428,"group":"All"}, {"name":"Kalash","size":7.64394707618749,"group":"All"}, {"name":"Lahu","size":10.4925065485976,"group":"All"}, {"name":"Mandenka","size":11.6337291372363,"group":"All"}, {"name":"Maya","size":6.21656313374935,"group":"All"}, {"name":"MbutiPygmy","size":9.59069692447837,"group":"All"}, {"name":"Melanesian","size":5.63754791677056,"group":"All"}, {"name":"Mongola","size":7.66595569922866,"group":"All"}, {"name":"Mozabite","size":8.28086822136265,"group":"All"}, {"name":"Palestinian","size":7.63413988461501,"group":"All"}, {"name":"Papuan","size":5,"group":"All"}, {"name":"Pima","size":5.90704095324958,"group":"All"}, {"name":"Russian","size":12.7750600060414,"group":"All"}, {"name":"San","size":15.3013346951557,"group":"All"}, {"name":"Uygur","size":9.92838043624162,"group":"All"}, {"name":"Yakut","size":9.23887506552157,"group":"All"}, {"name":"Yi","size":5.44276319089491,"group":"All"}, {"name":"Yoruba","size":10.8424595936733,"group":"All"}], "links":[{"source":0,"target":1,"weight":2.57488287436612}, {"source":0,"target":5,"weight":2.54719519391535}, {"source":0,"target":16,"weight":5.42789403731218}, {"source":0,"target":19,"weight":3.08558514190523}, {"source":0,"target":23,"weight":3.61110781180487}, {"source":0,"target":25,"weight":3.71440665711225}, {"source":1,"target":4,"weight":2.60118127045771}, {"source":1,"target":5,"weight":2.15694382014031}, {"source":1,"target":12,"weight":2.56513573539331}, {"source":1,"target":15,"weight":3.2434616674282}, {"source":2,"target":6,"weight":3.32798389609114}, {"source":2,"target":14,"weight":2.59590858884392}, {"source":2,"target":16,"weight":3.48262745307385}, {"source":2,"target":26,"weight":5.1398405112763}, {"source":2,"target":28,"weight":2.81476927959627}, {"source":3,"target":16,"weight":4.40179821828722}, {"source":3,"target":24,"weight":5.43647686695647}, {"source":3,"target":28,"weight":3.59875821414786}, {"source":4,"target":11,"weight":2.44738181535534}, {"source":4,"target":12,"weight":2.25598823275413}, {"source":4,"target":15,"weight":3.16768530247495}, {"source":4,"target":18,"weight":3.37152736032727}, {"source":4,"target":23,"weight":2.93483442151253}, {"source":5,"target":11,"weight":2.10657856985766}, {"source":5,"target":16,"weight":3.82748969904547}, {"source":5,"target":19,"weight":2.38666316644886}, {"source":5,"target":20,"weight":1.70788584175071}, {"source":6,"target":14,"weight":3.34104731703025}, {"source":6,"target":24,"weight":4.27856165200195}, {"source":6,"target":28,"weight":3.57982671668272}, {"source":7,"target":8,"weight":4.78381837776905}, {"source":7,"target":11,"weight":3.16799243937226}, {"source":7,"target":21,"weight":3.71273184321443}, {"source":7,"target":24,"weight":5.68196955921536}, {"source":7,"target":27,"weight":4.47126109311966}, {"source":8,"target":10,"weight":2.80405445550364}, {"source":8,"target":17,"weight":5.0658591267728}, {"source":8,"target":18,"weight":3.02936727308388}, {"source":8,"target":22,"weight":5.07645131599604}, {"source":8,"target":25,"weight":3.00025017535298}, {"source":8,"target":26,"weight":3.3351882046705}, {"source":8,"target":27,"weight":4.32345499702717}, {"source":9,"target":15,"weight":1.71438114046031}, {"source":9,"target":19,"weight":4.90120702229409}, {"source":9,"target":22,"weight":3.11781206389256}, {"source":9,"target":26,"weight":4.56075114804189}, {"source":10,"target":18,"weight":2.09843492626492}, {"source":10,"target":25,"weight":2.5614581192839}, {"source":10,"target":26,"weight":2.69060794749129}, {"source":10,"target":27,"weight":3.5405510939095}, {"source":11,"target":20,"weight":2.15460197715214}, {"source":11,"target":23,"weight":3.10334341267197}, {"source":11,"target":25,"weight":3.1877543265549}, {"source":12,"target":18,"weight":3.5843219101674}, {"source":12,"target":22,"weight":3.84291872490265}, {"source":13,"target":17,"weight":4.69526116227212}, {"source":13,"target":18,"weight":3.72675812379065}, {"source":13,"target":24,"weight":6.46128362598715}, {"source":13,"target":26,"weight":3.07956631157383}, {"source":13,"target":27,"weight":3.89252897151823}, {"source":14,"target":16,"weight":3.57404246028846}, {"source":14,"target":19,"weight":3.53949160825675}, {"source":14,"target":28,"weight":2.46776975360847}, {"source":15,"target":22,"weight":2.86392152300233}, {"source":16,"target":19,"weight":3.92357970984508}, {"source":16,"target":24,"weight":4.46736012190172}, {"source":17,"target":18,"weight":4.40922310339956}, {"source":17,"target":21,"weight":2.95899768672492}, {"source":18,"target":25,"weight":2.6588064109679}, {"source":19,"target":20,"weight":2.14975386211082}, {"source":19,"target":22,"weight":4.17555704727146}, {"source":25,"target":27,"weight":3.83357486150353}, {"source":26,"target":27,"weight":3.63076554717594}]
}
