{
 "nodes":[{"name":"Adygei","size":8.2202242269597,"group":"All"}, {"name":"Balochi","size":11.1324101552236,"group":"All"}, {"name":"BantuKenya","size":10.9610211192174,"group":"All"}, {"name":"BantuSouthAfrica","size":11.3284877641829,"group":"All"}, {"name":"Basque","size":7.76238962140892,"group":"All"}, {"name":"Bedouin","size":8.11151625411133,"group":"All"}, {"name":"BiakaPygmy","size":10.1588453160202,"group":"All"}, {"name":"Burusho","size":10.7777366342939,"group":"All"}, {"name":"Cambodian","size":8.74777949233167,"group":"All"}, {"name":"Colombian","size":5,"group":"All"}, {"name":"Daur","size":8.9745296594768,"group":"All"}, {"name":"Druze","size":8.25184243962383,"group":"All"}, {"name":"Kalash","size":6.81519023148386,"group":"All"}, {"name":"Lahu","size":8.68787053587082,"group":"All"}, {"name":"Mandenka","size":10.5814055523237,"group":"All"}, {"name":"Maya","size":5.75575183448341,"group":"All"}, {"name":"MbutiPygmy","size":10.0786962970749,"group":"All"}, {"name":"Melanesian","size":6.32629243550626,"group":"All"}, {"name":"Mongola","size":9.22884524207179,"group":"All"}, {"name":"Mozabite","size":8.6839284924225,"group":"All"}, {"name":"Palestinian","size":7.9039908488729,"group":"All"}, {"name":"Papuan","size":7.07491504568239,"group":"All"}, {"name":"Pima","size":6.63118752441124,"group":"All"}, {"name":"Russian","size":7.45281010848381,"group":"All"}, {"name":"San","size":19.5199327569877,"group":"All"}, {"name":"Uygur","size":10.9151544607625,"group":"All"}, {"name":"Yakut","size":10.5994507204029,"group":"All"}, {"name":"Yi","size":10.5785971126122,"group":"All"}, {"name":"Yoruba","size":9.62405645809167,"group":"All"}], "links":[{"source":0,"target":4,"weight":3.01666270089209}, {"source":0,"target":5,"weight":2.44612809269628}, {"source":0,"target":11,"weight":2.52522492222116}, {"source":0,"target":20,"weight":2.51630533682012}, {"source":1,"target":5,"weight":2.49630214575027}, {"source":1,"target":11,"weight":2.3508377035731}, {"source":1,"target":21,"weight":4.29320582560855}, {"source":1,"target":26,"weight":5.16784428378669}, {"source":1,"target":28,"weight":4.20656905717706}, {"source":2,"target":3,"weight":3.18760741842265}, {"source":2,"target":6,"weight":3.26823839074697}, {"source":2,"target":10,"weight":5.85140221628259}, {"source":2,"target":14,"weight":2.61802586806526}, {"source":2,"target":16,"weight":3.75161101808458}, {"source":2,"target":19,"weight":3.25069905496272}, {"source":2,"target":28,"weight":2.86261493097702}, {"source":3,"target":6,"weight":3.83658171332629}, {"source":3,"target":9,"weight":5.72282996712286}, {"source":3,"target":14,"weight":3.25695363031818}, {"source":3,"target":16,"weight":4.01094469941735}, {"source":3,"target":24,"weight":6.64872527257856}, {"source":4,"target":11,"weight":2.45789428440525}, {"source":4,"target":12,"weight":2.63072565689204}, {"source":4,"target":15,"weight":4.56044396600771}, {"source":4,"target":20,"weight":2.6771412516008}, {"source":4,"target":23,"weight":2.18815573615096}, {"source":4,"target":24,"weight":8.21401986446566}, {"source":5,"target":11,"weight":1.74453944500378}, {"source":5,"target":12,"weight":2.04655344709182}, {"source":5,"target":19,"weight":2.75149456226675}, {"source":5,"target":20,"weight":1.78509208303282}, {"source":5,"target":23,"weight":2.40256993321058}, {"source":5,"target":28,"weight":4.11928548010544}, {"source":6,"target":10,"weight":5.89107569497602}, {"source":6,"target":16,"weight":4.48083758534366}, {"source":6,"target":24,"weight":7.11799670997106}, {"source":7,"target":9,"weight":3.73008969810436}, {"source":7,"target":19,"weight":4.77796708814857}, {"source":7,"target":25,"weight":3.57975002390281}, {"source":7,"target":27,"weight":3.74181157842338}, {"source":8,"target":13,"weight":2.94616279089357}, {"source":8,"target":17,"weight":4.16515835003468}, {"source":8,"target":21,"weight":4.34942246408235}, {"source":8,"target":25,"weight":3.61873858108757}, {"source":8,"target":26,"weight":4.09759878550433}, {"source":9,"target":15,"weight":3.23456739333738}, {"source":9,"target":22,"weight":3.62486895293828}, {"source":10,"target":13,"weight":3.68032409670235}, {"source":10,"target":15,"weight":4.35848611832993}, {"source":10,"target":17,"weight":4.11659066115189}, {"source":10,"target":25,"weight":2.86425107713059}, {"source":10,"target":27,"weight":3.25459082246483}, {"source":11,"target":12,"weight":2.12644968878558}, {"source":11,"target":18,"weight":3.65007175961822}, {"source":11,"target":19,"weight":3.14743676288094}, {"source":11,"target":23,"weight":2.17720477049997}, {"source":12,"target":17,"weight":3.62063371534267}, {"source":12,"target":20,"weight":2.12345691546516}, {"source":12,"target":21,"weight":4.07760504450138}, {"source":12,"target":22,"weight":5.91270762606055}, {"source":13,"target":26,"weight":3.68660495039965}, {"source":13,"target":27,"weight":3.42741095934993}, {"source":14,"target":24,"weight":6.61590348023265}, {"source":14,"target":28,"weight":2.94039516136964}, {"source":15,"target":17,"weight":4.54462215528622}, {"source":15,"target":22,"weight":3.32817766575984}, {"source":15,"target":26,"weight":5.85996539890008}, {"source":15,"target":27,"weight":3.7150455247613}, {"source":16,"target":24,"weight":6.92062073679209}, {"source":17,"target":18,"weight":3.31374220669188}, {"source":17,"target":21,"weight":3.66864770240564}, {"source":18,"target":22,"weight":4.42833650645133}, {"source":18,"target":25,"weight":3.91507590043249}, {"source":18,"target":26,"weight":3.496471318455}, {"source":18,"target":27,"weight":3.59474580802999}, {"source":19,"target":28,"weight":3.77636107693769}, {"source":21,"target":26,"weight":4.65015669333735}, {"source":22,"target":27,"weight":3.05048689993008}, {"source":24,"target":26,"weight":8.31065599544466}, {"source":25,"target":26,"weight":3.4254422281011}, {"source":25,"target":27,"weight":3.00607707750035}, {"source":26,"target":27,"weight":3.70859629606876}]
}
