{
 "nodes":[{"name":"Adygei","size":7.05650166495423,"group":"All"}, {"name":"Balochi","size":11.0056773683641,"group":"All"}, {"name":"BantuKenya","size":9.82905273360066,"group":"All"}, {"name":"BantuSouthAfrica","size":11.1517127189574,"group":"All"}, {"name":"Basque","size":7.66647262438188,"group":"All"}, {"name":"Bedouin","size":8.21779933345692,"group":"All"}, {"name":"BiakaPygmy","size":14.2576483140527,"group":"All"}, {"name":"Burusho","size":9.15882258565216,"group":"All"}, {"name":"Cambodian","size":5.88044656626339,"group":"All"}, {"name":"Colombian","size":8.22431658922626,"group":"All"}, {"name":"Daur","size":6.68899588954917,"group":"All"}, {"name":"Druze","size":7.77306715177356,"group":"All"}, {"name":"Kalash","size":7.97039039234347,"group":"All"}, {"name":"Lahu","size":7.71910830147603,"group":"All"}, {"name":"Mandenka","size":11.9957028993595,"group":"All"}, {"name":"Maya","size":5,"group":"All"}, {"name":"MbutiPygmy","size":11.8984732312399,"group":"All"}, {"name":"Melanesian","size":5.8562152005995,"group":"All"}, {"name":"Mongola","size":8.16916940246947,"group":"All"}, {"name":"Mozabite","size":9.88102731280954,"group":"All"}, {"name":"Palestinian","size":8.71447613724738,"group":"All"}, {"name":"Papuan","size":6.22641091919603,"group":"All"}, {"name":"Pima","size":5.89067179839244,"group":"All"}, {"name":"Russian","size":7.64730009475615,"group":"All"}, {"name":"San","size":17.2982029968069,"group":"All"}, {"name":"Uygur","size":10.7076102958126,"group":"All"}, {"name":"Yakut","size":8.00244651079671,"group":"All"}, {"name":"Yi","size":6.02110869028463,"group":"All"}, {"name":"Yoruba","size":14.5933072068588,"group":"All"}], "links":[{"source":0,"target":1,"weight":2.35669741575114}, {"source":0,"target":5,"weight":1.95217810082119}, {"source":0,"target":9,"weight":4.42534207793104}, {"source":0,"target":12,"weight":2.76549336436879}, {"source":0,"target":20,"weight":1.99425586051449}, {"source":0,"target":23,"weight":2.15809794432858}, {"source":1,"target":5,"weight":2.47011836382379}, {"source":1,"target":7,"weight":2.89257123081623}, {"source":1,"target":25,"weight":2.27692944236961}, {"source":2,"target":14,"weight":3.99213780393094}, {"source":2,"target":16,"weight":4.84716764861498}, {"source":2,"target":19,"weight":3.35812324775245}, {"source":2,"target":24,"weight":4.75978864827041}, {"source":2,"target":28,"weight":3.63323695302041}, {"source":3,"target":6,"weight":4.46040503940502}, {"source":3,"target":14,"weight":3.6482320373719}, {"source":3,"target":16,"weight":5.28511856286644}, {"source":3,"target":28,"weight":3.71689936045308}, {"source":4,"target":5,"weight":2.40112031354372}, {"source":4,"target":11,"weight":2.7989675227046}, {"source":4,"target":19,"weight":3.08601588777468}, {"source":4,"target":20,"weight":2.19097450568364}, {"source":4,"target":26,"weight":3.63718632402836}, {"source":5,"target":7,"weight":3.71875789966987}, {"source":5,"target":8,"weight":2.47584820122684}, {"source":5,"target":11,"weight":2.52824330184764}, {"source":5,"target":19,"weight":2.7222387118562}, {"source":5,"target":20,"weight":2.05988416482349}, {"source":6,"target":14,"weight":3.99504958937926}, {"source":6,"target":16,"weight":4.58225501343998}, {"source":6,"target":24,"weight":5.54375603578927}, {"source":7,"target":18,"weight":3.08884836296392}, {"source":7,"target":20,"weight":4.04721312479751}, {"source":7,"target":21,"weight":6.35720171229933}, {"source":7,"target":22,"weight":4.15676796679319}, {"source":8,"target":10,"weight":2.15326007606682}, {"source":8,"target":13,"weight":2.03258621566535}, {"source":8,"target":18,"weight":2.14390697835349}, {"source":8,"target":26,"weight":2.70004035618225}, {"source":9,"target":15,"weight":2.26352452005885}, {"source":9,"target":16,"weight":7.46865970903758}, {"source":9,"target":22,"weight":3.35735217982902}, {"source":9,"target":23,"weight":3.70770749501579}, {"source":9,"target":26,"weight":3.1651851072833}, {"source":10,"target":13,"weight":1.88997639680484}, {"source":10,"target":15,"weight":2.35378751245113}, {"source":10,"target":25,"weight":2.01603063618444}, {"source":10,"target":27,"weight":1.86802450049663}, {"source":11,"target":12,"weight":3.19758417741729}, {"source":11,"target":20,"weight":2.54651321253035}, {"source":11,"target":23,"weight":2.61691298751648}, {"source":11,"target":24,"weight":5.20422989328543}, {"source":12,"target":18,"weight":3.41750092708126}, {"source":12,"target":20,"weight":2.88639899516465}, {"source":12,"target":23,"weight":2.90965487401433}, {"source":12,"target":25,"weight":2.73292311937628}, {"source":13,"target":18,"weight":1.87824175799424}, {"source":13,"target":25,"weight":2.23426625260237}, {"source":13,"target":27,"weight":1.98928790935019}, {"source":14,"target":19,"weight":4.22368964356923}, {"source":14,"target":24,"weight":5.26316908132481}, {"source":14,"target":28,"weight":2.93568720346966}, {"source":15,"target":22,"weight":2.57055798745206}, {"source":15,"target":26,"weight":2.65994565148157}, {"source":15,"target":27,"weight":2.35123356252353}, {"source":17,"target":21,"weight":3.33067925489086}, {"source":18,"target":22,"weight":3.67093357855853}, {"source":18,"target":27,"weight":2.36299507455834}, {"source":20,"target":22,"weight":4.8340791736482}, {"source":20,"target":24,"weight":4.88300727039746}, {"source":23,"target":26,"weight":2.98426726362314}, {"source":26,"target":27,"weight":2.51222068294538}]
}
