{
 "nodes":[{"name":"Adygei","size":5.56783357774357,"group":"All"}, {"name":"Balochi","size":7.98051221114454,"group":"All"}, {"name":"BantuKenya","size":11.8051181706605,"group":"All"}, {"name":"BantuSouthAfrica","size":10.6683970509057,"group":"All"}, {"name":"Basque","size":9.12301102488505,"group":"All"}, {"name":"Bedouin","size":8.68074902728492,"group":"All"}, {"name":"BiakaPygmy","size":10.7592171105058,"group":"All"}, {"name":"Burusho","size":8.70045039259537,"group":"All"}, {"name":"Cambodian","size":8.91184553977359,"group":"All"}, {"name":"Colombian","size":5.08721126453719,"group":"All"}, {"name":"Daur","size":6.87263711483716,"group":"All"}, {"name":"Druze","size":6.91599461112521,"group":"All"}, {"name":"Kalash","size":6.60942953742125,"group":"All"}, {"name":"Lahu","size":12.300721110761,"group":"All"}, {"name":"Mandenka","size":10.2461822464516,"group":"All"}, {"name":"Maya","size":5.4125384650023,"group":"All"}, {"name":"MbutiPygmy","size":12.6310822257989,"group":"All"}, {"name":"Melanesian","size":5,"group":"All"}, {"name":"Mongola","size":8.70128036438894,"group":"All"}, {"name":"Mozabite","size":7.65250460251444,"group":"All"}, {"name":"Palestinian","size":7.98825683312125,"group":"All"}, {"name":"Papuan","size":5.910293736457,"group":"All"}, {"name":"Pima","size":6.18104779535523,"group":"All"}, {"name":"Russian","size":6.27732379567185,"group":"All"}, {"name":"San","size":15.3279696967963,"group":"All"}, {"name":"Uygur","size":9.66373535087437,"group":"All"}, {"name":"Yakut","size":10.3019226508051,"group":"All"}, {"name":"Yi","size":16.995092915658,"group":"All"}, {"name":"Yoruba","size":11.0588704226496,"group":"All"}], "links":[{"source":0,"target":5,"weight":1.82061452967051}, {"source":0,"target":9,"weight":2.258787150354}, {"source":0,"target":11,"weight":1.81734429549729}, {"source":0,"target":12,"weight":1.82716259457878}, {"source":0,"target":20,"weight":1.64156397526218}, {"source":1,"target":5,"weight":2.33547292589821}, {"source":1,"target":7,"weight":2.41767156789644}, {"source":1,"target":11,"weight":2.33926402510436}, {"source":1,"target":12,"weight":2.6478920573081}, {"source":1,"target":22,"weight":3.45522829000585}, {"source":2,"target":3,"weight":3.98424051876977}, {"source":2,"target":14,"weight":3.79082863634324}, {"source":2,"target":16,"weight":8.19910683431946}, {"source":2,"target":24,"weight":6.72516459276319}, {"source":2,"target":27,"weight":5.35879381078081}, {"source":2,"target":28,"weight":3.70524541445756}, {"source":3,"target":6,"weight":4.55891766667205}, {"source":3,"target":24,"weight":6.29954749217245}, {"source":3,"target":28,"weight":3.91939090125373}, {"source":4,"target":5,"weight":3.17401307953678}, {"source":4,"target":9,"weight":2.86915925187642}, {"source":4,"target":12,"weight":2.58550897448653}, {"source":4,"target":17,"weight":4.17483370074034}, {"source":4,"target":20,"weight":2.43698138840256}, {"source":4,"target":23,"weight":2.32918692985303}, {"source":4,"target":25,"weight":2.93462294265893}, {"source":5,"target":7,"weight":2.60158332065873}, {"source":5,"target":11,"weight":1.55720347572698}, {"source":5,"target":15,"weight":2.21686676186796}, {"source":5,"target":19,"weight":2.14481180414537}, {"source":5,"target":20,"weight":1.62787859429927}, {"source":6,"target":14,"weight":3.76286431958505}, {"source":6,"target":16,"weight":4.97805890757607}, {"source":6,"target":24,"weight":5.50249587235065}, {"source":6,"target":28,"weight":3.73809698609993}, {"source":7,"target":8,"weight":4.91625919207593}, {"source":7,"target":10,"weight":2.93296288315243}, {"source":7,"target":12,"weight":2.86179238920159}, {"source":7,"target":13,"weight":4.39856679830354}, {"source":8,"target":10,"weight":3.10997855601247}, {"source":8,"target":13,"weight":3.43564620128492}, {"source":8,"target":21,"weight":2.94446537978966}, {"source":8,"target":25,"weight":3.66554277133505}, {"source":8,"target":26,"weight":3.16731384314922}, {"source":8,"target":27,"weight":3.71462510752013}, {"source":9,"target":12,"weight":2.40720085724811}, {"source":9,"target":15,"weight":2.50653715759242}, {"source":9,"target":19,"weight":3.35555624619701}, {"source":9,"target":22,"weight":3.64875416463533}, {"source":9,"target":23,"weight":2.37270240948955}, {"source":10,"target":12,"weight":3.0426705814885}, {"source":10,"target":17,"weight":3.60229594966842}, {"source":10,"target":18,"weight":2.11262653741099}, {"source":10,"target":19,"weight":2.53479099408081}, {"source":10,"target":22,"weight":3.42760875858643}, {"source":10,"target":23,"weight":3.42135315951146}, {"source":10,"target":25,"weight":2.59082893865159}, {"source":11,"target":20,"weight":1.32585713512748}, {"source":11,"target":22,"weight":3.64303275174887}, {"source":11,"target":23,"weight":1.82810516977849}, {"source":12,"target":20,"weight":1.99931073439419}, {"source":12,"target":23,"weight":2.75957708268986}, {"source":13,"target":21,"weight":3.73788740882541}, {"source":13,"target":24,"weight":7.91192376032422}, {"source":14,"target":16,"weight":5.48857291756348}, {"source":14,"target":28,"weight":2.02373250756794}, {"source":15,"target":18,"weight":1.73136605819543}, {"source":15,"target":22,"weight":3.01351897352749}, {"source":15,"target":23,"weight":2.24096062506753}, {"source":16,"target":24,"weight":8.47600173828741}, {"source":17,"target":19,"weight":3.57177306278792}, {"source":17,"target":20,"weight":4.39409613713419}, {"source":17,"target":21,"weight":2.85402227878076}, {"source":18,"target":21,"weight":2.97858102636831}, {"source":18,"target":22,"weight":3.24797714635433}, {"source":18,"target":26,"weight":2.53784884172096}, {"source":18,"target":27,"weight":3.49421518272809}, {"source":19,"target":20,"weight":2.06751682054001}, {"source":19,"target":22,"weight":4.15193637220385}, {"source":19,"target":25,"weight":2.50943812357587}, {"source":20,"target":23,"weight":1.76871686650045}, {"source":22,"target":24,"weight":7.7224141544406}, {"source":23,"target":26,"weight":3.53376875165556}, {"source":25,"target":27,"weight":4.07501171605713}, {"source":26,"target":27,"weight":3.49067638044039}]
}
