{
 "nodes":[{"name":"Adygei","size":5.80410686282036,"group":"All"}, {"name":"Balochi","size":7.42102324765489,"group":"All"}, {"name":"BantuKenya","size":12.5808337615662,"group":"All"}, {"name":"BantuSouthAfrica","size":12.148563594519,"group":"All"}, {"name":"Basque","size":6.99434945467916,"group":"All"}, {"name":"Bedouin","size":8.31057456945666,"group":"All"}, {"name":"BiakaPygmy","size":14.4019463009887,"group":"All"}, {"name":"Burusho","size":9.46007914138481,"group":"All"}, {"name":"Cambodian","size":6.94544352318796,"group":"All"}, {"name":"Colombian","size":6.66187798511456,"group":"All"}, {"name":"Daur","size":6.70733539501974,"group":"All"}, {"name":"Druze","size":6.87939205198035,"group":"All"}, {"name":"Kalash","size":5.63403029302646,"group":"All"}, {"name":"Lahu","size":6.39216087631878,"group":"All"}, {"name":"Mandenka","size":11.362225925091,"group":"All"}, {"name":"Maya","size":6.542926131078,"group":"All"}, {"name":"MbutiPygmy","size":16.3873836994447,"group":"All"}, {"name":"Melanesian","size":6.28772531112252,"group":"All"}, {"name":"Mongola","size":6.08702066939884,"group":"All"}, {"name":"Mozabite","size":7.64269183911236,"group":"All"}, {"name":"Palestinian","size":7.64338923012034,"group":"All"}, {"name":"Papuan","size":7.13932170841951,"group":"All"}, {"name":"Pima","size":5,"group":"All"}, {"name":"Russian","size":8.09948234482655,"group":"All"}, {"name":"San","size":18.8157098935573,"group":"All"}, {"name":"Uygur","size":7.0042037458851,"group":"All"}, {"name":"Yakut","size":6.56433288715512,"group":"All"}, {"name":"Yi","size":7.64356024935475,"group":"All"}, {"name":"Yoruba","size":11.20556890544,"group":"All"}], "links":[{"source":0,"target":11,"weight":1.8980266042991}, {"source":0,"target":12,"weight":2.29564100222145}, {"source":0,"target":20,"weight":2.3671821848368}, {"source":0,"target":26,"weight":2.07580071930702}, {"source":1,"target":4,"weight":2.47951412157419}, {"source":1,"target":5,"weight":2.25731396608327}, {"source":1,"target":7,"weight":2.50680184956293}, {"source":1,"target":12,"weight":2.28887674448858}, {"source":1,"target":20,"weight":2.13892483405216}, {"source":1,"target":23,"weight":2.11667068496943}, {"source":1,"target":25,"weight":2.08088192799637}, {"source":2,"target":6,"weight":4.14690619327117}, {"source":2,"target":16,"weight":8.00540716244706}, {"source":2,"target":19,"weight":4.95653404428613}, {"source":2,"target":28,"weight":2.8628061000445}, {"source":3,"target":6,"weight":5.04692513986842}, {"source":3,"target":14,"weight":4.37707436669779}, {"source":3,"target":15,"weight":7.83495040310045}, {"source":3,"target":16,"weight":8.28456427889028}, {"source":3,"target":28,"weight":3.62550099898698}, {"source":4,"target":8,"weight":6.09034406895445}, {"source":4,"target":11,"weight":2.1878611923548}, {"source":4,"target":12,"weight":3.07971774624154}, {"source":4,"target":20,"weight":2.48090348734557}, {"source":4,"target":22,"weight":3.48369162789075}, {"source":4,"target":23,"weight":2.65161738220864}, {"source":4,"target":25,"weight":3.69140323972622}, {"source":5,"target":11,"weight":1.68352240752613}, {"source":5,"target":12,"weight":2.76768052474622}, {"source":5,"target":19,"weight":2.48760563971648}, {"source":5,"target":20,"weight":1.94442374502126}, {"source":6,"target":14,"weight":4.61512695141249}, {"source":6,"target":24,"weight":12.6185785635732}, {"source":6,"target":28,"weight":4.39336607685028}, {"source":7,"target":12,"weight":3.02007003806046}, {"source":7,"target":17,"weight":3.224163492993}, {"source":7,"target":21,"weight":2.79921216114969}, {"source":7,"target":22,"weight":3.67449100854796}, {"source":7,"target":25,"weight":2.63738199528495}, {"source":8,"target":10,"weight":3.26983739133009}, {"source":8,"target":24,"weight":13.4234458488258}, {"source":8,"target":27,"weight":2.6917383127779}, {"source":9,"target":13,"weight":5.26057785187779}, {"source":9,"target":17,"weight":3.68730975045005}, {"source":9,"target":22,"weight":2.40780553383727}, {"source":10,"target":18,"weight":2.60680841274557}, {"source":10,"target":21,"weight":3.00393076463445}, {"source":10,"target":26,"weight":2.13620150461954}, {"source":10,"target":27,"weight":3.05834892447673}, {"source":11,"target":20,"weight":1.85446490542509}, {"source":11,"target":22,"weight":3.28899414069966}, {"source":11,"target":23,"weight":2.16018755432218}, {"source":12,"target":15,"weight":6.64817936589461}, {"source":12,"target":19,"weight":3.09022472339792}, {"source":12,"target":20,"weight":3.25191815151956}, {"source":12,"target":22,"weight":4.63464029183773}, {"source":12,"target":23,"weight":2.44219078720751}, {"source":13,"target":18,"weight":2.94535970925056}, {"source":13,"target":27,"weight":2.43532145842312}, {"source":14,"target":19,"weight":5.16837568074048}, {"source":14,"target":28,"weight":3.16511229763418}, {"source":15,"target":16,"weight":9.60394138946923}, {"source":15,"target":22,"weight":5.02193811354911}, {"source":15,"target":24,"weight":14.746249327805}, {"source":16,"target":24,"weight":13.3119539555967}, {"source":17,"target":21,"weight":2.93705945329671}, {"source":17,"target":25,"weight":3.23827045197347}, {"source":18,"target":25,"weight":2.22136353801166}, {"source":18,"target":26,"weight":2.42984211112301}, {"source":18,"target":27,"weight":2.93304126425331}, {"source":19,"target":20,"weight":2.39526283230166}, {"source":20,"target":25,"weight":2.83787571856996}, {"source":21,"target":25,"weight":3.51486977911487}, {"source":21,"target":26,"weight":2.84077104739038}, {"source":23,"target":24,"weight":13.3907365027988}]
}
