{
 "nodes":[{"name":"Adygei","size":6.00297348913114,"group":"All"}, {"name":"Balochi","size":8.66371644375658,"group":"All"}, {"name":"BantuKenya","size":10.2904325190929,"group":"All"}, {"name":"BantuSouthAfrica","size":11.5409283711276,"group":"All"}, {"name":"Basque","size":7.25586446257192,"group":"All"}, {"name":"Bedouin","size":7.76485164094105,"group":"All"}, {"name":"BiakaPygmy","size":10.9866847041557,"group":"All"}, {"name":"Burusho","size":5.27453477954116,"group":"All"}, {"name":"Cambodian","size":9.1208007466877,"group":"All"}, {"name":"Colombian","size":7.77566874635699,"group":"All"}, {"name":"Daur","size":8.06966475331537,"group":"All"}, {"name":"Druze","size":7.32878402931945,"group":"All"}, {"name":"Kalash","size":6.81986415641378,"group":"All"}, {"name":"Lahu","size":8.69377257866053,"group":"All"}, {"name":"Mandenka","size":10.0314745673148,"group":"All"}, {"name":"Maya","size":9.62271195276869,"group":"All"}, {"name":"MbutiPygmy","size":14.8418531898139,"group":"All"}, {"name":"Melanesian","size":6.77011748295228,"group":"All"}, {"name":"Mongola","size":10.0827828111555,"group":"All"}, {"name":"Mozabite","size":8.78610450155047,"group":"All"}, {"name":"Palestinian","size":7.51572895643532,"group":"All"}, {"name":"Papuan","size":5,"group":"All"}, {"name":"Pima","size":10.9029655232947,"group":"All"}, {"name":"Russian","size":7.02680804455432,"group":"All"}, {"name":"San","size":18.1411067736969,"group":"All"}, {"name":"Uygur","size":7.99840744592433,"group":"All"}, {"name":"Yakut","size":7.94274269460386,"group":"All"}, {"name":"Yi","size":12.1252607257519,"group":"All"}, {"name":"Yoruba","size":11.0351076737144,"group":"All"}], "links":[{"source":0,"target":11,"weight":1.79459960178266}, {"source":0,"target":20,"weight":1.54836811507005}, {"source":0,"target":23,"weight":1.69920031639297}, {"source":0,"target":26,"weight":2.34080675491189}, {"source":1,"target":7,"weight":2.81438824738067}, {"source":1,"target":8,"weight":2.87113185266127}, {"source":1,"target":11,"weight":2.30660896752833}, {"source":1,"target":12,"weight":2.53950701994475}, {"source":1,"target":27,"weight":3.46419569097043}, {"source":2,"target":3,"weight":3.86953080315044}, {"source":2,"target":6,"weight":4.26282578711676}, {"source":2,"target":14,"weight":3.41756662204533}, {"source":2,"target":18,"weight":5.66800348121309}, {"source":2,"target":20,"weight":4.47694650246289}, {"source":2,"target":28,"weight":4.39855862839712}, {"source":3,"target":6,"weight":3.84525539862471}, {"source":3,"target":14,"weight":2.46870891146223}, {"source":3,"target":16,"weight":5.36944451225225}, {"source":3,"target":28,"weight":4.08191984453578}, {"source":4,"target":5,"weight":2.82134095216623}, {"source":4,"target":7,"weight":2.27967574981392}, {"source":4,"target":11,"weight":2.12280769135323}, {"source":4,"target":13,"weight":3.10036353898613}, {"source":4,"target":21,"weight":2.50299076618174}, {"source":4,"target":23,"weight":2.14963546864226}, {"source":4,"target":25,"weight":3.17929007645499}, {"source":5,"target":11,"weight":1.980353411475}, {"source":5,"target":12,"weight":2.97827192293224}, {"source":5,"target":19,"weight":2.39263017736274}, {"source":5,"target":20,"weight":2.3290008825523}, {"source":5,"target":21,"weight":3.77345610653902}, {"source":6,"target":14,"weight":3.53268673588913}, {"source":6,"target":16,"weight":4.6023480109758}, {"source":7,"target":13,"weight":3.71347401723525}, {"source":7,"target":21,"weight":2.35060726568631}, {"source":7,"target":23,"weight":2.07426304953795}, {"source":7,"target":25,"weight":2.52936460777772}, {"source":8,"target":9,"weight":4.82824709371484}, {"source":8,"target":12,"weight":2.34732898517085}, {"source":8,"target":13,"weight":2.90728223555404}, {"source":8,"target":18,"weight":4.14342244534526}, {"source":8,"target":25,"weight":2.98899515795622}, {"source":9,"target":13,"weight":5.07934231375855}, {"source":9,"target":15,"weight":4.83154094959995}, {"source":9,"target":24,"weight":10.7419937986797}, {"source":10,"target":13,"weight":2.78905901092264}, {"source":10,"target":18,"weight":2.82634038284424}, {"source":10,"target":23,"weight":2.50273477111738}, {"source":10,"target":25,"weight":2.38294523582485}, {"source":10,"target":27,"weight":2.60430773080575}, {"source":11,"target":17,"weight":2.60546559692763}, {"source":11,"target":20,"weight":1.89440308715608}, {"source":11,"target":23,"weight":1.45733788848764}, {"source":12,"target":21,"weight":1.95782521908374}, {"source":12,"target":26,"weight":2.2288916267347}, {"source":13,"target":18,"weight":3.42027561980119}, {"source":13,"target":26,"weight":2.30113716601416}, {"source":13,"target":27,"weight":2.80906199245095}, {"source":14,"target":28,"weight":2.98680818570342}, {"source":15,"target":17,"weight":2.91024119388705}, {"source":15,"target":22,"weight":4.44017370321787}, {"source":15,"target":27,"weight":2.55239985357669}, {"source":16,"target":24,"weight":8.50910420938677}, {"source":17,"target":21,"weight":1.88341066547553}, {"source":17,"target":25,"weight":2.24561519800908}, {"source":17,"target":26,"weight":1.7552419290253}, {"source":18,"target":22,"weight":4.84164579984617}, {"source":18,"target":27,"weight":3.28676170379451}, {"source":19,"target":20,"weight":2.13390839486017}, {"source":19,"target":23,"weight":2.29255611648288}, {"source":22,"target":24,"weight":10.1467457030698}, {"source":23,"target":25,"weight":2.18601547195492}, {"source":24,"target":28,"weight":9.04767857515768}, {"source":25,"target":26,"weight":2.20246579252065}, {"source":25,"target":27,"weight":2.21994801168915}]
}
